mazebox/__init__.py
mazebox/_settings.py
mazebox/archetypes/__init__.py
mazebox/archetypes/_bulk_signature.py
mazebox/archetypes/_cell_state_space.py
mazebox/archetypes/_intra_inter_heterogeneity.py
mazebox/archetypes/_signature_scoring.py
mazebox/network/__init__.py
mazebox/network/generate_timepoints.py
mazebox/plasticity/__init__.py
mazebox/plasticity/_ctrp.py
mazebox/plasticity/_utils.py
mazebox/plasticity/_velocity.py
mazebox/plotting/__init__.py
mazebox/plotting/_archetype_plots.py
mazebox/plotting/_circular_projection.py
mazebox/plotting/_network_plots.py
mazebox/plotting/_plasticity_plots.py
mazebox/plotting/_utils.py
mazebox/preprocessing/__init__.py
mazebox/preprocessing/_filter.py
mazebox/preprocessing/_imputation.py
mazebox/preprocessing/_integrate.py
mazebox/preprocessing/_read.py
mazebox-0.0.3.dist-info/LICENSE
mazebox-0.0.3.dist-info/METADATA
mazebox-0.0.3.dist-info/WHEEL
mazebox-0.0.3.dist-info/top_level.txt
mazebox-0.0.3.dist-info/RECORD
